MANIFEST.in
README
__init__.py
__pkginfo__.py
entities.py
hooks.py
schema.py
secutils.py
setup.py
testutils.py
utils.py
views.py
cubicweb_container.egg-info/PKG-INFO
cubicweb_container.egg-info/SOURCES.txt
cubicweb_container.egg-info/dependency_links.txt
cubicweb_container.egg-info/not-zip-safe
cubicweb_container.egg-info/requires.txt
cubicweb_container.egg-info/top_level.txt
i18n/en.po
i18n/es.po
i18n/fr.po
migration/1.0.0_Any.py
migration/2.5.0_Any.py
migration/postcreate.py
test/pytestconf.py
test/unittest_circus.py
test/unittest_entities.py
test/unittest_rclone.py
test/unittest_schema.py
test/unittest_security.py
test4/unittest_security.py