Metadata-Version: 1.0
Name: cubicweb-container
Version: 2.6.1
Summary: provides "generic container" services
Home-page: http://www.cubicweb.org/project/cubicweb-container
Author: LOGILAB S.A. (Paris, FRANCE)
Author-email: contact@logilab.fr
License: LGPL
Platform: UNKNOWN
